{
  "base_price": 2995,
  "beamstation_catalog_url": "https://beamstation.com/datasets",
  "beamstation_origin": "https://beamstation.com",
  "category_group_name": "Restaurants",
  "config_category": "sales",
  "config_description": "--High-Volume, Active targets--\n\nPopular restaurants sitting in the Top 30% of their local market for proven foot traffic and review volume within the last 90 days and a city-wide market scope.\n\nThese are the highest-velocity, actively transacting accounts for payment processing, POS systems, and supply chain sales.\n\nValidated by an \"Active Heartbeat\" signal.",
  "config_name": "Top 30% Active Restaurant Whales in Houston, US",
  "export_job_id": "ebe44781-1454-476f-be3f-f3ab74bed734",
  "github_org": "Beamstation-Datasets",
  "id_short": 459982,
  "location_name": "Houston",
  "location_type": "city",
  "repo_name": "top-30-active-restaurant-whales-in-houston-us-sample-459982",
  "sample_b2_path": "b2-export:BeamStation-ExportFiles/459982/beamstation_459982_restaurants-us-tx_SAMPLE_DIST.csv",
  "sample_pct": 9.83,
  "sample_records": 46,
  "sample_sha256": "8cf33c4ca5c954110425e73df17beabe58c76099688cf772828c7ac630b4b583",
  "sample_size_bytes": 208696,
  "total_records": 468,
  "updated_at": "2026-04-29T12:59:16.297620+00:00"
}